yasa/__init__.py
yasa/detection.py
yasa/evaluation.py
yasa/features.py
yasa/heart.py
yasa/hypno.py
yasa/io.py
yasa/numba.py
yasa/others.py
yasa/plotting.py
yasa/sleepstats.py
yasa/spectral.py
yasa/staging.py
yasa/classifiers/clf_eeg+demo_lgb_0.5.0.joblib
yasa/classifiers/clf_eeg+emg+demo_lgb_0.5.0.joblib
yasa/classifiers/clf_eeg+emg_lgb_0.5.0.joblib
yasa/classifiers/clf_eeg+eog+demo_lgb_0.5.0.joblib
yasa/classifiers/clf_eeg+eog+emg+demo_lgb_0.4.0.joblib
yasa/classifiers/clf_eeg+eog+emg+demo_lgb_0.5.0.joblib
yasa/classifiers/clf_eeg+eog+emg_lgb_0.4.0.joblib
yasa/classifiers/clf_eeg+eog+emg_lgb_0.5.0.joblib
yasa/classifiers/clf_eeg+eog_lgb_0.4.0.joblib
yasa/classifiers/clf_eeg+eog_lgb_0.5.0.joblib
yasa/classifiers/clf_eeg_lgb_0.4.0.joblib
yasa/classifiers/clf_eeg_lgb_0.5.0.joblib
yasa-0.6.5.dist-info/LICENSE
yasa-0.6.5.dist-info/METADATA
yasa-0.6.5.dist-info/WHEEL
yasa-0.6.5.dist-info/top_level.txt
yasa-0.6.5.dist-info/RECORD
