Metadata-Version: 2.1
Name: yasa
Version: 0.6.5
Summary: YASA: Analysis of polysomnography recordings.
Home-page: https://github.com/raphaelvallat/yasa/
Download-URL: https://github.com/raphaelvallat/yasa/
Author: Raphael Vallat
Author-email: raphaelvallat9@gmail.com
Maintainer: Raphael Vallat
Maintainer-email: raphaelvallat9@gmail.com
License: BSD (3-clause)
Classifier: Intended Audience :: Science/Research
Classifier: Programming Language :: Python :: 3.8
Classifier: Programming Language :: Python :: 3.9
Classifier: Programming Language :: Python :: 3.10
Classifier: Programming Language :: Python :: 3.11
Classifier: License :: OSI Approved :: BSD License
Classifier: Operating System :: POSIX
Classifier: Operating System :: Unix
Classifier: Operating System :: MacOS
License-File: LICENSE
Requires-Dist: numpy (>=1.18.1)
Requires-Dist: scipy
Requires-Dist: pandas
Requires-Dist: matplotlib
Requires-Dist: seaborn
Requires-Dist: mne (>=1.3)
Requires-Dist: numba (>=0.57.1)
Requires-Dist: antropy
Requires-Dist: scikit-learn
Requires-Dist: tensorpac (>=0.6.5)
Requires-Dist: pyriemann (>=0.2.7)
Requires-Dist: sleepecg (>=0.5.0)
Requires-Dist: lspopt
Requires-Dist: ipywidgets
Requires-Dist: joblib
Requires-Dist: lightgbm
